leonardo_ai/__init__.py
leonardo_ai/app.py
leonardo_ai/app2.py
leonardo_ai/leonardo_ai.py
LeonardoAIGenPy-0.1.1.dist-info/METADATA
LeonardoAIGenPy-0.1.1.dist-info/WHEEL
LeonardoAIGenPy-0.1.1.dist-info/top_level.txt
LeonardoAIGenPy-0.1.1.dist-info/RECORD
